poa/__init__.py
poa/alignment.py
poa/edge.py
poa/graph.py
poa/node.py
poa/seq.py
poa-0.0.1.dist-info/METADATA
poa-0.0.1.dist-info/WHEEL
poa-0.0.1.dist-info/top_level.txt
poa-0.0.1.dist-info/RECORD
