Metadata-Version: 2.1
Name: poa
Version: 0.0.1
Summary: A simple partial order alignment implement.
Home-page: https://github.com/dwpeng/poa
Author: dwpeng
Author-email: 1732889554@qq.com
License: UNKNOWN
Platform: UNKNOWN
Requires-Python: >=3.6
Requires-Dist: numpy
